tapback/__init__.py
tapback/constants.py
tapback/server.py
tapback/tapback.py
tapback/tapback_mcp.py
tapback-0.1.8.dist-info/METADATA
tapback-0.1.8.dist-info/WHEEL
tapback-0.1.8.dist-info/entry_points.txt
tapback-0.1.8.dist-info/licenses/LICENSE
tapback-0.1.8.dist-info/RECORD
