Metadata-Version: 2.4
Name: tapback
Version: 0.1.8
Summary: Tapback - Mobile approval tool for LLM workflows
Project-URL: Homepage, https://github.com/mk1018/tapback
Project-URL: Repository, https://github.com/mk1018/tapback
Author: motonari kurita
License-Expression: MIT
License-File: LICENSE
Keywords: claude code,cli,codex,llm,mcp,vibe coding
Classifier: Development Status :: 4 - Beta
Classifier: Environment :: Console
Classifier: Intended Audience :: Developers
Classifier: License :: OSI Approved :: MIT License
Classifier: Programming Language :: Python :: 3.10
Classifier: Programming Language :: Python :: 3.11
Classifier: Programming Language :: Python :: 3.12
Classifier: Programming Language :: Python :: 3.13
Requires-Python: >=3.10
Requires-Dist: fastapi>=0.115.0
Requires-Dist: mcp>=1.25.0
Requires-Dist: python-multipart>=0.0.20
Requires-Dist: requests>=2.32.5
Requires-Dist: uvicorn>=0.34.0
Requires-Dist: websockets>=14.0
